[
  {
    "id": "budget-focused/index",
    "collection": "pages",
    "url": "/budget-focused",
    "primaryKeyword": "budget wedding venues denver",
    "intent": "commercial",
    "dimension": "feature"
  },
  {
    "id": "events/index",
    "collection": "pages",
    "url": "/events",
    "primaryKeyword": "event venues denver",
    "intent": "commercial",
    "dimension": "occasion"
  },
  {
    "id": "index",
    "collection": "pages",
    "url": "/",
    "primaryKeyword": "penelopes venue",
    "intent": "navigational",
    "dimension": "style"
  },
  {
    "id": "planning/index",
    "collection": "pages",
    "url": "/planning",
    "primaryKeyword": "event planning denver",
    "intent": "informational",
    "dimension": "occasion",
    "citySlug": "westminster"
  },
  {
    "id": "seasonal/christmas/index",
    "collection": "pages",
    "url": "/seasonal/christmas",
    "primaryKeyword": "christmas party venue westminster",
    "intent": "commercial",
    "dimension": "season",
    "citySlug": "westminster",
    "season": "holiday"
  },
  {
    "id": "seasonal/fall-wedding-venue-denver",
    "collection": "pages",
    "url": "/seasonal/fall-wedding-venue-denver",
    "primaryKeyword": "fall wedding venue denver",
    "intent": "commercial",
    "dimension": "season",
    "season": "fall"
  },
  {
    "id": "seasonal/holiday/arvada",
    "collection": "pages",
    "url": "/seasonal/holiday/arvada",
    "primaryKeyword": "holiday party venue arvada",
    "intent": "commercial",
    "dimension": "season",
    "citySlug": "arvada",
    "season": "holiday"
  },
  {
    "id": "seasonal/holiday/broomfield",
    "collection": "pages",
    "url": "/seasonal/holiday/broomfield",
    "primaryKeyword": "holiday party venue broomfield",
    "intent": "commercial",
    "dimension": "season",
    "citySlug": "broomfield",
    "season": "holiday"
  },
  {
    "id": "seasonal/holiday/denver",
    "collection": "pages",
    "url": "/seasonal/holiday/denver",
    "primaryKeyword": "holiday party venue denver",
    "intent": "commercial",
    "dimension": "season",
    "citySlug": "denver",
    "season": "holiday"
  },
  {
    "id": "seasonal/holiday/index",
    "collection": "pages",
    "url": "/seasonal/holiday",
    "citySlug": "westminster",
    "season": "holiday"
  },
  {
    "id": "seasonal/holiday/lakewood",
    "collection": "pages",
    "url": "/seasonal/holiday/lakewood",
    "primaryKeyword": "holiday party venue lakewood",
    "intent": "commercial",
    "dimension": "season",
    "citySlug": "lakewood",
    "season": "holiday"
  },
  {
    "id": "seasonal/holiday/thornton",
    "collection": "pages",
    "url": "/seasonal/holiday/thornton",
    "primaryKeyword": "holiday party venue thornton",
    "intent": "commercial",
    "dimension": "season",
    "citySlug": "thornton",
    "season": "holiday"
  },
  {
    "id": "seasonal/index",
    "collection": "pages",
    "url": "/seasonal",
    "primaryKeyword": "seasonal wedding venue denver",
    "intent": "informational",
    "dimension": "season",
    "citySlug": "westminster"
  },
  {
    "id": "seasonal/new-years/index",
    "collection": "pages",
    "url": "/seasonal/new-years",
    "primaryKeyword": "new years eve venue westminster",
    "intent": "commercial",
    "dimension": "occasion",
    "citySlug": "westminster",
    "season": "holiday"
  },
  {
    "id": "seasonal/spring-wedding-venue-denver",
    "collection": "pages",
    "url": "/seasonal/spring-wedding-venue-denver",
    "primaryKeyword": "spring wedding venue denver",
    "intent": "commercial",
    "dimension": "season",
    "season": "spring"
  },
  {
    "id": "seasonal/summer-wedding-venue-denver",
    "collection": "pages",
    "url": "/seasonal/summer-wedding-venue-denver",
    "primaryKeyword": "summer wedding venue denver",
    "intent": "commercial",
    "dimension": "season",
    "season": "summer"
  },
  {
    "id": "seasonal/winter-wedding-venue-denver",
    "collection": "pages",
    "url": "/seasonal/winter-wedding-venue-denver",
    "primaryKeyword": "winter wedding venue denver",
    "intent": "commercial",
    "dimension": "season",
    "season": "winter"
  },
  {
    "id": "venue-types/hacienda-wedding-venue-denver",
    "collection": "pages",
    "url": "/venue-types/hacienda-wedding-venue-denver",
    "primaryKeyword": "hacienda wedding venue denver",
    "intent": "commercial",
    "dimension": "style",
    "citySlug": "denver"
  },
  {
    "id": "venue-types/spanish-style-wedding-venue-colorado",
    "collection": "pages",
    "url": "/venue-types/spanish-style-wedding-venue-colorado",
    "primaryKeyword": "spanish style wedding venue colorado",
    "intent": "commercial",
    "dimension": "style",
    "canonicalOf": "/venue-types/spanish-wedding-venue"
  },
  {
    "id": "arvada",
    "collection": "service-areas",
    "url": "/service-areas/arvada",
    "primaryKeyword": "wedding venue arvada",
    "intent": "commercial",
    "dimension": "city",
    "citySlug": "arvada"
  },
  {
    "id": "aurora",
    "collection": "service-areas",
    "url": "/service-areas/aurora",
    "primaryKeyword": "wedding venue aurora",
    "intent": "commercial",
    "dimension": "city",
    "citySlug": "aurora"
  },
  {
    "id": "broomfield",
    "collection": "service-areas",
    "url": "/service-areas/broomfield",
    "primaryKeyword": "wedding venue broomfield",
    "intent": "commercial",
    "dimension": "city",
    "citySlug": "broomfield"
  },
  {
    "id": "commerce-city",
    "collection": "service-areas",
    "url": "/service-areas/commerce-city",
    "primaryKeyword": "wedding venue commerce city",
    "intent": "commercial",
    "dimension": "city",
    "citySlug": "commerce-city"
  },
  {
    "id": "denver",
    "collection": "service-areas",
    "url": "/service-areas/denver",
    "primaryKeyword": "wedding venue denver",
    "intent": "commercial",
    "dimension": "city",
    "citySlug": "denver"
  },
  {
    "id": "englewood",
    "collection": "service-areas",
    "url": "/service-areas/englewood",
    "primaryKeyword": "wedding venue englewood",
    "intent": "commercial",
    "dimension": "city",
    "citySlug": "englewood"
  },
  {
    "id": "lakewood",
    "collection": "service-areas",
    "url": "/service-areas/lakewood",
    "primaryKeyword": "wedding venue lakewood",
    "intent": "commercial",
    "dimension": "city",
    "citySlug": "lakewood"
  },
  {
    "id": "littleton",
    "collection": "service-areas",
    "url": "/service-areas/littleton",
    "primaryKeyword": "wedding venue littleton",
    "intent": "commercial",
    "dimension": "city",
    "citySlug": "littleton"
  },
  {
    "id": "northglenn",
    "collection": "service-areas",
    "url": "/service-areas/northglenn",
    "primaryKeyword": "wedding venue northglenn",
    "intent": "commercial",
    "dimension": "city",
    "citySlug": "northglenn"
  },
  {
    "id": "thornton",
    "collection": "service-areas",
    "url": "/service-areas/thornton",
    "primaryKeyword": "wedding venue thornton",
    "intent": "commercial",
    "dimension": "city",
    "citySlug": "thornton"
  },
  {
    "id": "westminster",
    "collection": "service-areas",
    "url": "/service-areas/westminster",
    "primaryKeyword": "wedding venue westminster co",
    "intent": "commercial",
    "dimension": "city",
    "citySlug": "westminster"
  },
  {
    "id": "wheat-ridge",
    "collection": "service-areas",
    "url": "/service-areas/wheat-ridge",
    "primaryKeyword": "wedding venue wheat ridge",
    "intent": "commercial",
    "dimension": "city",
    "citySlug": "wheat-ridge"
  }
]